{
  "generatedAt": "2026-07-19",
  "totalAll": 299345,
  "total7d": 17286,
  "publicAll": 255036,
  "privateAll": 44309,
  "public7d": 11747,
  "private7d": 5539,
  "repos": [
    {
      "name": "web3game",
      "private": false,
      "lang": "Rust",
      "all": 61448,
      "d7": 3347
    },
    {
      "name": "GlucoseGit",
      "private": false,
      "lang": "TypeScript",
      "all": 60537,
      "d7": 4741
    },
    {
      "name": "ultra-sync",
      "private": false,
      "lang": "Rust",
      "all": 55187,
      "d7": 0
    },
    {
      "name": "eegprev",
      "private": false,
      "lang": "EJS",
      "all": 31042,
      "d7": 0
    },
    {
      "name": "web3game-logs",
      "private": true,
      "lang": null,
      "all": 28973,
      "d7": 515
    },
    {
      "name": "VRchatFACE-HAND-ARM-tracking",
      "private": false,
      "lang": "Rust",
      "all": 22760,
      "d7": 0
    },
    {
      "name": "gogames",
      "private": false,
      "lang": "JavaScript",
      "all": 15788,
      "d7": 0
    },
    {
      "name": "web3game-launcher",
      "private": true,
      "lang": "Rust",
      "all": 10909,
      "d7": 5024
    },
    {
      "name": "Simulateur-d-emergence-D-eterministe",
      "private": false,
      "lang": "Rust",
      "all": 8274,
      "d7": 3659
    },
    {
      "name": "spike01-unreal",
      "private": true,
      "lang": "C++",
      "all": 4427,
      "d7": 0
    }
  ]
}